pipelet/__init__.py
pipelet/decarators/__init__.py
pipelet/decarators/logging_decorator.py
pipelet/decarators/option_decorator.py
pipelet/etl/__init__.py
pipelet/etl/extract/__init__.py
pipelet/etl/extract/http/__init__.py
pipelet/etl/extract/http/http_extractor.py
pipelet/etl/transform/__init__.py
pipelet/etl/transform/csv/__init__.py
pipelet/etl/transform/csv/reader.py
pipelet/etl/transform/json/__init__.py
pipelet/etl/transform/json/reader.py
pipelet/etl/transform/unzip/__init__.py
pipelet/etl/transform/unzip/base.py
pipelet/etl/transform/unzip/tar_processor.py
pipelet/exceptions/__init__.py
pipelet/exceptions/base.py
pipelet/exceptions/csv_processor.py
pipelet/exceptions/download_processor.py
pipelet/exceptions/file_system.py
pipelet/exceptions/unzip_processor.py
pipelet/factories/__init__.py
pipelet/factories/exceptions_factory.py
pipelet/factories/file_system_factory.py
pipelet/log/__init__.py
pipelet/log/logger.py
pipelet/operations/__init__.py
pipelet/operations/operations.py
pipelet/operations/pipeline.py
pipelet/operations/yaml_pipeline_loader.py
pipelet/processors/__init__.py
pipelet/processors/abc.py
pipelet/processors/base.py
pipelet/processors/chain_processors/__init__.py
pipelet/processors/chain_processors/base.py
pipelet/processors/file_system/__init__.py
pipelet/processors/file_system/base.py
pipelet/processors/file_system/file_system_types.py
pipelet/processors/meta.py
pipelet/processors/mixins.py
pipelet/processors/processor_types.py
pipelet/processors/retry_processor.py
pipelet/processors/splitter_processor.py
pipelet/storage/__init__.py
pipelet/storage/abc.py
pipelet/storage/local_storage.py
pipelet/storage/storage_manager.py
pipelet/utils/__init__.py
pipelet/utils/common.py
pipelet-0.0.16.dist-info/LICENSE
pipelet-0.0.16.dist-info/METADATA
pipelet-0.0.16.dist-info/WHEEL
pipelet-0.0.16.dist-info/RECORD
